odoo/addons/product_ingredient/README.rst
odoo/addons/product_ingredient/__init__.py
odoo/addons/product_ingredient/__manifest__.py
odoo/addons/product_ingredient/hooks.py
odoo/addons/product_ingredient/data/product_allergen_data.xml
odoo/addons/product_ingredient/i18n/es.po
odoo/addons/product_ingredient/i18n/product_ingredient.pot
odoo/addons/product_ingredient/models/__init__.py
odoo/addons/product_ingredient/models/product_attribute.py
odoo/addons/product_ingredient/models/product_attribute_value.py
odoo/addons/product_ingredient/models/product_ingredient.py
odoo/addons/product_ingredient/models/product_ingredient_value.py
odoo/addons/product_ingredient/models/product_product.py
odoo/addons/product_ingredient/models/product_template.py
odoo/addons/product_ingredient/models/production_lot_ingredient_value.py
odoo/addons/product_ingredient/models/stock_production_lot.py
odoo/addons/product_ingredient/readme/CONTRIBUTORS.rst
odoo/addons/product_ingredient/readme/DESCRIPTION.rst
odoo/addons/product_ingredient/readme/USAGE.rst
odoo/addons/product_ingredient/security/ir.model.access.csv
odoo/addons/product_ingredient/static/description/icon.png
odoo/addons/product_ingredient/static/description/index.html
odoo/addons/product_ingredient/views/product_attribute_value_views.xml
odoo/addons/product_ingredient/views/product_ingredient_views.xml
odoo/addons/product_ingredient/views/product_views.xml
odoo/addons/product_ingredient/views/stock_production_lot_view.xml
odoo_addon_product_ingredient-15.0.1.0.0.6.dist-info/METADATA
odoo_addon_product_ingredient-15.0.1.0.0.6.dist-info/WHEEL
odoo_addon_product_ingredient-15.0.1.0.0.6.dist-info/top_level.txt
odoo_addon_product_ingredient-15.0.1.0.0.6.dist-info/RECORD
