Metadata-Version: 2.1
Name: odoo-addon-product_ingredient
Version: 15.0.1.0.0.6
Summary: Product ingredients
Home-page: https://github.com/OCA/product-attribute
Author: Tecnativa, Odoo Community Association (OCA)
Author-email: support@odoo-community.org
License: AGPL-3
Classifier: Programming Language :: Python
Classifier: Framework :: Odoo
Classifier: Framework :: Odoo :: 15.0
Classifier: License :: OSI Approved :: GNU Affero General Public License v3
Classifier: Development Status :: 4 - Beta
Requires-Python: >=3.8
Requires-Dist: odoo<15.1dev,>=15.0a
Requires-Dist: openupgradelib
